oggm/__init__.py
oggm/cfg.py
oggm/exceptions.py
oggm/global_tasks.py
oggm/graphics.py
oggm/mpi.py
oggm/params.cfg
oggm/tasks.py
oggm/workflow.py
oggm/cli/__init__.py
oggm/cli/benchmark.py
oggm/cli/netrc_credentials.py
oggm/cli/prepro_levels.py
oggm/core/__init__.py
oggm/core/centerlines.py
oggm/core/climate.py
oggm/core/dynamic_spinup.py
oggm/core/flowline.py
oggm/core/gis.py
oggm/core/inversion.py
oggm/core/massbalance.py
oggm/core/sia2d.py
oggm/data/Alaska_albers_V3.json
oggm/data/AntarcticDEM_wgs84.json
oggm/data/REMA_100m_dem.json
oggm/data/arcticdem_mosaic_100m_v3.0.json
oggm/data/dem_sources.txt
oggm/data/demo_glaciers.csv
oggm/data/gimpdem_90m_v01.1.json
oggm/sandbox/__init__.py
oggm/sandbox/calving_fabi.py
oggm/sandbox/calving_jan.py
oggm/sandbox/distribute_2d.py
oggm/sandbox/edu.py
oggm/sandbox/pygem_compat.py
oggm/shop/__init__.py
oggm/shop/bedtopo.py
oggm/shop/cook23.py
oggm/shop/cru.py
oggm/shop/ecmwf.py
oggm/shop/gcm_climate.py
oggm/shop/glathida.py
oggm/shop/histalp.py
oggm/shop/hugonnet_maps.py
oggm/shop/its_live.py
oggm/shop/millan22.py
oggm/shop/rgitopo.py
oggm/shop/w5e5.py
oggm/tests/__init__.py
oggm/tests/__main__.py
oggm/tests/conftest.py
oggm/tests/funcs.py
oggm/tests/test_benchmarks.py
oggm/tests/test_graphics.py
oggm/tests/test_minimal.py
oggm/tests/test_models.py
oggm/tests/test_numerics.py
oggm/tests/test_prepro.py
oggm/tests/test_sandbox.py
oggm/tests/test_shop.py
oggm/tests/test_utils.py
oggm/tests/test_workflow.py
oggm/tests/ext/__init__.py
oggm/tests/ext/sia_fluxlim.py
oggm/utils/__init__.py
oggm/utils/_downloads.py
oggm/utils/_funcs.py
oggm/utils/_workflow.py
oggm-1.6.2.dist-info/LICENSE.txt
oggm-1.6.2.dist-info/METADATA
oggm-1.6.2.dist-info/WHEEL
oggm-1.6.2.dist-info/entry_points.txt
oggm-1.6.2.dist-info/top_level.txt
oggm-1.6.2.dist-info/RECORD
