Metadata-Version: 2.1
Name: oggm
Version: 1.6.2
Summary: Open Global Glacier Model
Home-page: https://oggm.org
Author: OGGM Contributors
Author-email: fabien.maussion@uibk.ac.at
License: BSD 3-clause
Project-URL: Documentation, https://oggm.readthedocs.io/
Project-URL: Source, https://github.com/OGGM/oggm
Project-URL: Tracker, https://github.com/OGGM/oggm/issues
Classifier: Development Status :: 4 - Beta
Classifier: Intended Audience :: Science/Research
Classifier: License :: OSI Approved :: BSD License
Classifier: Programming Language :: Python :: 3
Classifier: Programming Language :: Python :: 3.8
Classifier: Programming Language :: Python :: 3.9
Classifier: Programming Language :: Python :: 3.10
Classifier: Programming Language :: Python :: 3.11
Requires-Python: >=3.6
License-File: LICENSE.txt
Requires-Dist: numpy
Requires-Dist: scipy
Requires-Dist: pandas
Requires-Dist: matplotlib
Requires-Dist: shapely
Requires-Dist: requests
Requires-Dist: configobj
Requires-Dist: netcdf4
Requires-Dist: xarray
